qlab/controllers/APTMotor.py
qlab/controllers/IDQ800.py
qlab/controllers/KeithleyPowerSupply.py
qlab/controllers/LeoniFiberSwitch.py
qlab/controllers/__init__.py
qlab/utils/__init__.py
qlab/utils/hom_plot.py
qlab/utils/permanent.cp36-win_amd64.pyd
qlab-1.1.dist-info/DESCRIPTION.rst
qlab-1.1.dist-info/METADATA
qlab-1.1.dist-info/RECORD
qlab-1.1.dist-info/WHEEL
qlab-1.1.dist-info/metadata.json
qlab-1.1.dist-info/top_level.txt
