Metadata-Version: 2.0
Name: qlab
Version: 1.1
Summary: qlab is a Python package that provides methods useful to the Quantum Information Lab @ La Sapienza.
Home-page: https://github.com/matpompili/qlab/
Author: Matteo Pompili
Author-email: matpompili@gmail.com
License: GNU
Download-URL: https://github.com/matpompili/qlab/archive/v1.1-beta.tar.gz
Platform: UNKNOWN
Classifier: Development Status :: 4 - Beta
Classifier: Environment :: Console
Classifier: License :: OSI Approved :: GNU General Public License v3 or later (GPLv3+)
Classifier: Intended Audience :: Science/Research
Classifier: Programming Language :: Python :: 3
Classifier: Programming Language :: Python :: Implementation :: CPython
Classifier: Topic :: Scientific/Engineering :: Physics
Requires-Dist: numpy
Requires-Dist: pyvisa
